{"assets/fonts/Itim.ttf":["assets/fonts/Itim.ttf"],"assets/fonts/Myriad.ttf":["assets/fonts/Myriad.ttf"],"assets/fonts/fs.ttf":["assets/fonts/fs.ttf"],"assets/icons/github.svg":["assets/icons/github.svg"],"assets/icons/linkdin.svg":["assets/icons/linkdin.svg"],"assets/icons/triangle_left.svg":["assets/icons/triangle_left.svg"],"assets/icons/triangle_right.svg":["assets/icons/triangle_right.svg"],"assets/icons/whatsapp.svg":["assets/icons/whatsapp.svg"],"assets/images/logo.png":["assets/images/logo.png"],"assets/images/man.jpg":["assets/images/man.jpg"],"assets/images/man2.jpg":["assets/images/man2.jpg"],"assets/images/my_image.png":["assets/images/my_image.png"],"packages/cupertino_icons/assets/CupertinoIcons.ttf":["packages/cupertino_icons/assets/CupertinoIcons.ttf"]}